plover_mod_z/__init__.py
plover_mod_z/system.py
plover_mod_z-0.1.0.dist-info/LICENSE
plover_mod_z-0.1.0.dist-info/METADATA
plover_mod_z-0.1.0.dist-info/WHEEL
plover_mod_z-0.1.0.dist-info/entry_points.txt
plover_mod_z-0.1.0.dist-info/top_level.txt
plover_mod_z-0.1.0.dist-info/zip-safe
plover_mod_z-0.1.0.dist-info/RECORD
